truckscenes/__init__.py
truckscenes/truckscenes.py
truckscenes/eval/__init__.py
truckscenes/eval/common/__init__.py
truckscenes/eval/common/config.py
truckscenes/eval/common/constants.py
truckscenes/eval/common/data_classes.py
truckscenes/eval/common/loaders.py
truckscenes/eval/common/render.py
truckscenes/eval/common/utils.py
truckscenes/eval/detection/README.md
truckscenes/eval/detection/__init__.py
truckscenes/eval/detection/algo.py
truckscenes/eval/detection/config.py
truckscenes/eval/detection/constants.py
truckscenes/eval/detection/data_classes.py
truckscenes/eval/detection/evaluate.py
truckscenes/eval/detection/render.py
truckscenes/eval/detection/utils.py
truckscenes/eval/detection/configs/detection_cvpr_2024.json
truckscenes/utils/__init__.py
truckscenes/utils/colormap.py
truckscenes/utils/data_classes.py
truckscenes/utils/geometry_utils.py
truckscenes/utils/splits.py
truckscenes/utils/visualization_utils.py
truckscenes_devkit-1.0.0.dist-info/METADATA
truckscenes_devkit-1.0.0.dist-info/WHEEL
truckscenes_devkit-1.0.0.dist-info/top_level.txt
truckscenes_devkit-1.0.0.dist-info/RECORD
