Metadata-Version: 2.1
Name: truckscenes-devkit
Version: 1.0.0
Summary: Official development kit of the MAN TruckScenes dataset (www.man.eu/truckscenes).
Home-page: https://github.com/TUMFTM/truckscenes-devkit
Author: Felix Fent, Fabian Kuttenreich, Florian Ruch, Farija Rizwin
Author-email: truckscenes@man.eu
License: Apache-2.0
Keywords: MAN,TruckScenes,dataset,devkit,perception
Platform: linux
Platform: windows
Classifier: Intended Audience :: Developers
Classifier: Intended Audience :: Education
Classifier: Intended Audience :: Science/Research
Classifier: License :: OSI Approved :: Apache Software License
Classifier: Natural Language :: English
Classifier: Operating System :: OS Independent
Classifier: Programming Language :: Python :: 3
Classifier: Programming Language :: Python :: 3 :: Only
Classifier: Programming Language :: Python :: 3.6
Classifier: Programming Language :: Python :: 3.7
Classifier: Programming Language :: Python :: 3.8
Classifier: Programming Language :: Python :: 3.9
Classifier: Programming Language :: Python :: 3.10
Classifier: Programming Language :: Python :: 3.11
Classifier: Topic :: Scientific/Engineering :: Artificial Intelligence
Requires-Python: >=3.6
Requires-Dist: numpy
Requires-Dist: pyquaternion >=0.9.5
Requires-Dist: tqdm
Requires-Dist: pypcd4
Provides-Extra: all
Requires-Dist: matplotlib ; extra == 'all'
Requires-Dist: jupyter ; extra == 'all'
Requires-Dist: open3d ; extra == 'all'
Requires-Dist: opencv-python ; extra == 'all'
Requires-Dist: Pillow >6.2.1 ; extra == 'all'
Provides-Extra: visu
Requires-Dist: matplotlib ; extra == 'visu'
Requires-Dist: open3d ; extra == 'visu'
Requires-Dist: opencv-python ; extra == 'visu'
Requires-Dist: Pillow >6.2.1 ; extra == 'visu'
